lammpstools/__init__.py
lammpstools/baseclass.py
lammpstools/condensedarray.py
lammpstools/dumploader.py
lammpstools/dumptovtk.py
lammpstools/histogramloader.py
lammpstools/logloader.py
lammpstools/readdata.py
lammpstools/vtktodump.py
lammpstools-0.0.20.dist-info/LICENSE
lammpstools-0.0.20.dist-info/METADATA
lammpstools-0.0.20.dist-info/WHEEL
lammpstools-0.0.20.dist-info/top_level.txt
lammpstools-0.0.20.dist-info/RECORD
