Metadata-Version: 2.1
Name: lammpstools
Version: 0.0.20
Summary: package to analyse LAMMPS data
Home-page: https://github.com/samueljmcameron/LAMMPStools
Author: Sam Cameron
Author-email: samuel.j.m.cameron@gmail.com
Classifier: Programming Language :: Python :: 3
Classifier: License :: OSI Approved :: GNU General Public License v3 (GPLv3)
Classifier: Operating System :: OS Independent
Requires-Python: >=3.3
License-File: LICENSE
Requires-Dist: numpy
